mlops_misis2025/__init__.py
mlops_misis2025/config.py
mlops_misis2025/dataset.py
mlops_misis2025/features.py
mlops_misis2025/plots.py
mlops_misis2025/utils.py
mlops_misis2025/inference/00_make_requests.py
mlops_misis2025/inference/01_batch_inference.py
mlops_misis2025/inference/02_online_inference.py
mlops_misis2025/inference/__init__.py
mlops_misis2025/modeling/__init__.py
mlops_misis2025/modeling/predict.py
mlops_misis2025/modeling/train.py
mlops_misis2025-0.0.1.dist-info/WHEEL
mlops_misis2025-0.0.1.dist-info/METADATA
mlops_misis2025-0.0.1.dist-info/RECORD
