Metadata-Version: 2.4
Name: mlops_misis2025
Version: 0.0.1
Summary: A short description of the project.
Author: Alexey Myshlyanov
Requires-Python: ~=3.13.0
Classifier: Programming Language :: Python :: 3
Requires-Dist: boto3>=1.40.54
Requires-Dist: catboost>=1.2.8
Requires-Dist: dvc>=3.63.0
Requires-Dist: fastapi[standard]>=0.118.3
Requires-Dist: gepa>=0.0.17
Requires-Dist: hyperopt>=0.2.7
Requires-Dist: jupyter>=1.1.1
Requires-Dist: litellm>=1.78.2
Requires-Dist: loguru
Requires-Dist: mkdocs
Requires-Dist: mlflow==3.5.0
Requires-Dist: numpy>=2.3.3
Requires-Dist: openai>=2.4.0
Requires-Dist: pandas>=2.3.3
Requires-Dist: pip
Requires-Dist: psycopg2-binary>=2.9.11
Requires-Dist: pydantic>=2.11.9
Requires-Dist: pydantic-yaml>=1.6.0
Requires-Dist: pytest>=8.4.2
Requires-Dist: python-dotenv
Requires-Dist: pyyaml>=6.0.2
Requires-Dist: ruff
Requires-Dist: scikit-learn>=1.7.2
Requires-Dist: sqlalchemy>=2.0.43
Requires-Dist: tensorflow>=2.20.0
Requires-Dist: torch>=2.9.0
Requires-Dist: torchinfo>=1.8.0
Requires-Dist: torchvision>=0.24.0
Requires-Dist: tqdm
Requires-Dist: typer
